cubo_harmonic/__init__.py
cubo_harmonic/spatial.py
cubo_harmonic/spectral.py
cubo_harmonic/utils.py
cubo_harmonic-0.0.2.dist-info/LICENSE
cubo_harmonic-0.0.2.dist-info/METADATA
cubo_harmonic-0.0.2.dist-info/WHEEL
cubo_harmonic-0.0.2.dist-info/RECORD
