Metadata-Version: 2.1
Name: cubo_harmonic
Version: 0.0.2
Summary: This is a template repository for Python projects that use Poetry for their dependency management.
Home-page: https://github.com/csaybar/cubo-harmonic
Author: Cesar Aybar
Author-email: fcesar.aybar@uv.es
Requires-Python: >=3.8,<4.0
Classifier: Programming Language :: Python :: 3
Classifier: Programming Language :: Python :: 3.8
Classifier: Programming Language :: Python :: 3.9
Classifier: Programming Language :: Python :: 3.10
Classifier: Programming Language :: Python :: 3.11
Requires-Dist: opensr-test (>=0.0.7,<0.0.8)
Requires-Dist: scikit-learn (>=1.3.2,<2.0.0)
Requires-Dist: torch (>=2.1.1,<3.0.0)
Project-URL: Documentation, https://csaybar.github.io/cubo-harmonic/
Project-URL: Repository, https://github.com/csaybar/cubo-harmonic
